License
pypi_count/.gitkeep
pypi_count/__init__.py
pypi_count/command_line_interface.py
pypi_count/py_counter.py
pypi_counter-0.3.2.dist-info/entry_points.txt
pypi_counter-0.3.2.dist-info/LICENSE
pypi_counter-0.3.2.dist-info/WHEEL
pypi_counter-0.3.2.dist-info/METADATA
pypi_counter-0.3.2.dist-info/RECORD
