Metadata-Version: 2.1
Name: pypi-counter
Version: 0.3.2
Summary: A counting program used for different Python packages and modules.
Home-page: https://github.com/cmpsc-481-s22-m1/PyPiCounter/tree/main
License: MIT
Author: Adriana Solis
Author-email: solisa@allegheny.edu
Requires-Python: >=3.7,<4.0
Classifier: License :: OSI Approved :: MIT License
Classifier: Programming Language :: Python :: 3
Classifier: Programming Language :: Python :: 3.10
Classifier: Programming Language :: Python :: 3.7
Classifier: Programming Language :: Python :: 3.8
Classifier: Programming Language :: Python :: 3.9
Requires-Dist: libcst (>=0.4.0,<0.5.0)
Requires-Dist: rich (>=10.9.0,<11.0.0)
Requires-Dist: typer[all] (>=0.3.2,<0.4.0)
Project-URL: Repository, https://github.com/cmpsc-481-s22-m1/PyPiCounter/tree/main
